pyglet/__init__.py
pyglet/__init__.pyi
pyglet/clock.py
pyglet/customtypes.py
pyglet/event.py
pyglet/info.py
pyglet/lib.py
pyglet/math.py
pyglet/py.typed
pyglet/resource.py
pyglet/shapes.py
pyglet/sprite.py
pyglet/util.py
pyglet/app/__init__.py
pyglet/app/base.py
pyglet/app/cocoa.py
pyglet/app/win32.py
pyglet/app/xlib.py
pyglet/display/__init__.py
pyglet/display/__init__.pyi
pyglet/display/base.py
pyglet/display/cocoa.py
pyglet/display/headless.py
pyglet/display/win32.py
pyglet/display/xlib.py
pyglet/display/xlib_vidmoderestore.py
pyglet/experimental/README.md
pyglet/experimental/geoshader_sprite.py
pyglet/experimental/hidraw.py
pyglet/experimental/jobs.py
pyglet/experimental/multitexture_sprite.py
pyglet/experimental/net.py
pyglet/experimental/particles.py
pyglet/extlibs/__init__.py
pyglet/extlibs/earcut.py
pyglet/extlibs/png.py
pyglet/font/__init__.py
pyglet/font/base.py
pyglet/font/fontconfig.py
pyglet/font/freetype.py
pyglet/font/freetype_lib.py
pyglet/font/quartz.py
pyglet/font/ttf.py
pyglet/font/user.py
pyglet/font/win32.py
pyglet/font/dwrite/__init__.py
pyglet/font/dwrite/d2d1_lib.py
pyglet/font/dwrite/d2d1_types_lib.py
pyglet/font/dwrite/dwrite_lib.py
pyglet/font/harfbuzz/__init__.py
pyglet/font/harfbuzz/harfbuzz_lib.py
pyglet/gl/__init__.py
pyglet/gl/agl.py
pyglet/gl/base.py
pyglet/gl/cocoa.py
pyglet/gl/gl.py
pyglet/gl/gl_compat.py
pyglet/gl/gl_info.py
pyglet/gl/glx.py
pyglet/gl/glx_info.py
pyglet/gl/glxext_arb.py
pyglet/gl/glxext_mesa.py
pyglet/gl/glxext_nv.py
pyglet/gl/headless.py
pyglet/gl/lib.py
pyglet/gl/lib_agl.py
pyglet/gl/lib_glx.py
pyglet/gl/lib_wgl.py
pyglet/gl/wgl.py
pyglet/gl/wgl_info.py
pyglet/gl/wglext_arb.py
pyglet/gl/wglext_nv.py
pyglet/gl/win32.py
pyglet/gl/xlib.py
pyglet/graphics/__init__.py
pyglet/graphics/allocation.py
pyglet/graphics/instance.py
pyglet/graphics/shader.py
pyglet/graphics/vertexarray.py
pyglet/graphics/vertexbuffer.py
pyglet/graphics/vertexdomain.py
pyglet/gui/__init__.py
pyglet/gui/frame.py
pyglet/gui/ninepatch.py
pyglet-2.1.5.dist-info/LICENSE
pyglet-2.1.5.dist-info/WHEEL
pyglet-2.1.5.dist-info/METADATA
pyglet-2.1.5.dist-info/RECORD
